.bumpversion.cfg
.coveragerc
AUTHORS.rst
CHANGELOG.rst
CONTRIBUTING.rst
MANIFEST.in
README.rst
requirements.txt
setup.cfg
setup.py
test.requirements.txt
tox.ini
src/Untitled.ipynb
src/client_config.json
src/sql.db
src/.algolink/metadata.json
src/.algolink/artifacts/datasets/0/train_input/data.pd
src/.algolink/artifacts/datasets/0/train_output/data.npz
src/.algolink/artifacts/model/0/methods.json
src/.algolink/artifacts/model/0/model.pkl
src/.algolink/artifacts/model/0/requirements.json
src/.algolink/artifacts/model/1/methods.json
src/.algolink/artifacts/model/1/model.pkl
src/.algolink/artifacts/model/1/requirements.json
src/.ipynb_checkpoints/Untitled-checkpoint.ipynb
src/.ipynb_checkpoints/client_config-checkpoint.json
src/algolink/__init__.py
src/algolink/config.py
src/algolink.egg-info/PKG-INFO
src/algolink.egg-info/SOURCES.txt
src/algolink.egg-info/dependency_links.txt
src/algolink.egg-info/entry_points.txt
src/algolink.egg-info/not-zip-safe
src/algolink.egg-info/requires.txt
src/algolink.egg-info/top_level.txt
src/algolink/.ipynb_checkpoints/__init__-checkpoint.py
src/algolink/.ipynb_checkpoints/config-checkpoint.py
src/algolink/build/__init__.py
src/algolink/build/helpers.py
src/algolink/build/.ipynb_checkpoints/__init__-checkpoint.py
src/algolink/build/.ipynb_checkpoints/helpers-checkpoint.py
src/algolink/build/builder/__init__.py
src/algolink/build/builder/base.py
src/algolink/build/builder/.ipynb_checkpoints/__init__-checkpoint.py
src/algolink/build/builder/.ipynb_checkpoints/base-checkpoint.py
src/algolink/build/provider/__init__.py
src/algolink/build/provider/base.py
src/algolink/build/provider/ml_model.py
src/algolink/build/provider/ml_model_multi.py
src/algolink/build/provider/pipeline.py
src/algolink/build/provider/utils.py
src/algolink/build/provider/.ipynb_checkpoints/__init__-checkpoint.py
src/algolink/build/provider/.ipynb_checkpoints/base-checkpoint.py
src/algolink/build/provider/.ipynb_checkpoints/ml_model-checkpoint.py
src/algolink/build/provider/.ipynb_checkpoints/ml_model_multi-checkpoint.py
src/algolink/build/provider/.ipynb_checkpoints/pipeline-checkpoint.py
src/algolink/build/provider/.ipynb_checkpoints/utils-checkpoint.py
src/algolink/build/runner/__init__.py
