Metadata-Version: 2.1
Name: algolink
Version: 0.7.17
Summary: Machine Learning Lifecycle Framework
Home-page: https://github.com/leepand/algolink
Author: Leepand
Author-email: leepand6@gmail.com
License: Apache-2.0
Project-URL: Changelog, https://github.com/leepand/algolink/blob/master/CHANGELOG.rst
Project-URL: Issue Tracker, https://github.com/leepand/algolink/issues
Platform: UNKNOWN
Classifier: Development Status :: 5 - Production/Stable
Classifier: Intended Audience :: Developers
Classifier: License :: OSI Approved :: Apache Software License
Classifier: Operating System :: Unix
Classifier: Operating System :: POSIX
Classifier: Operating System :: Microsoft :: Windows
Classifier: Programming Language :: Python
Classifier: Programming Language :: Python :: 3.6
Classifier: Programming Language :: Python :: 3.7
Classifier: Topic :: Utilities
Requires-Python: >=3.6
Provides-Extra: testing
License-File: AUTHORS.rst
